pyqtier/__init__.py
pyqtier/extra.py
pyqtier/pqr_managers.py
pyqtier/plugins/__init__.py
pyqtier/plugins/plugins.py
pyqtier/plugins/can_plugin/__init__.py
pyqtier/plugins/can_plugin/auxiliary.py
pyqtier/plugins/can_plugin/manager.py
pyqtier/plugins/can_plugin/models/__init__.py
pyqtier/plugins/can_plugin/models/can_model.py
pyqtier/plugins/can_plugin/models/data_processor.py
pyqtier/plugins/can_plugin/views/__init__.py
pyqtier/plugins/can_plugin/views/can_control.py
pyqtier/plugins/modbus_plugin/__init__.py
pyqtier/plugins/modbus_plugin/manager.py
pyqtier/plugins/modbus_plugin/models/__init__.py
pyqtier/plugins/modbus_plugin/models/data_processor.py
pyqtier/plugins/modbus_plugin/models/modbus_model.py
pyqtier/plugins/modbus_plugin/views/__init__.py
pyqtier/plugins/modbus_plugin/views/modbus_control.py
pyqtier/plugins/modbus_plugin/views/modbus_control_with_baudrate.py
pyqtier/plugins/usb_plugin/__init__.py
pyqtier/plugins/usb_plugin/auxiliary.py
pyqtier/plugins/usb_plugin/manager.py
pyqtier/plugins/usb_plugin/models/__init__.py
pyqtier/plugins/usb_plugin/models/data_processor.py
pyqtier/plugins/usb_plugin/models/serial_model.py
pyqtier/plugins/usb_plugin/views/__init__.py
pyqtier/plugins/usb_plugin/views/usb_control.py
pyqtier/plugins/usb_plugin/views/usb_control_with_baudrate.py
pyqtier/scripts/__init__.py
pyqtier/scripts/cli.py
pyqtier/scripts/config.py
pyqtier/scripts/converter.py
pyqtier/scripts/generator.py
pyqtier/scripts/generator_templates/__init__.py
pyqtier/scripts/generator_templates/config_templates.py
pyqtier/scripts/generator_templates/main_templates.py
pyqtier/scripts/generator_templates/manager_templates.py
pyqtier/scripts/generator_templates/resources_templates.py
pyqtier/scripts/generator_templates/ui_templates.py
pyqtier/scripts/generator_templates/views_templates.py
pyqtier/scripts/generator_templates/widget_templates.py
pyqtier/scripts/generator_templates/img/information.png
pyqtier/scripts/generator_templates/img/settings.png
pyqtier-1.2.0.dist-info/licenses/LICENSE
pyqtier-1.2.0.dist-info/METADATA
pyqtier-1.2.0.dist-info/WHEEL
pyqtier-1.2.0.dist-info/entry_points.txt
pyqtier-1.2.0.dist-info/top_level.txt
pyqtier-1.2.0.dist-info/RECORD
